dipend/__init__.py
dipend/dependency_container.py
dipend/dependency_container_config.py
dipend/__seedwork/__init__.py
dipend/__seedwork/base_checker.py
dipend/__seedwork/dictionary.py
dipend/__seedwork/handler_interface.py
dipend/__seedwork/strategy_interface.py
dipend/commands/__init__.py
dipend/commands/add_dependency_command.py
dipend/commands/add_dependency_command_handler.py
dipend/commands/resolve_dependency_command.py
dipend/commands/resolve_dependency_command_handler.py
dipend/commands/resolve_specific_lifecycles_command.py
dipend/commands/resolve_specific_lifecycles_command_handler.py
dipend/context/__init__.py
dipend/context/context_store.py
dipend/decorators/__init__.py
dipend/decorators/inject_mapped_dependency.py
dipend/dependency/__init__.py
dipend/dependency/dependency_registry.py
dipend/dependency/dependency_resolver.py
dipend/dependency/dependency_store.py
dipend/dependency/implementation_details.py
dipend/dependency/strategies/__init__.py
dipend/dependency/strategies/base_resolve_lifecycle_strategy.py
dipend/dependency/strategies/resolve_context_lifecycle_strategy.py
dipend/dependency/strategies/resolve_lifecycle_strategy_input.py
dipend/dependency/strategies/resolve_singleton_lifecycle_strategy.py
dipend/dependency/strategies/resolve_transient_lifecycle_strategy.py
dipend/enums/__init__.py
dipend/enums/lifecycle_enum.py
dipend/enums/token_type_enum.py
dipend/exceptions/__init__.py
dipend/exceptions/base_dependency_container_exception.py
dipend/exceptions/can_not_construct_dependency_exception.py
dipend/exceptions/cyclic_dependencies_exception.py
dipend/exceptions/decorator_exception.py
dipend/exceptions/exception_handler.py
dipend/exceptions/invalid_lifecycle_exception.py
dipend/exceptions/missing_dependency_exception.py
dipend/exceptions/missing_dependency_token_exception.py
dipend/helpers/__init__.py
dipend/helpers/inspect_class_helper.py
dipend/token/__init__.py
dipend/token/token_name_resolver.py
dipend/token/token_registry.py
dipend-1.0.0.dist-info/licenses/LICENSE
dipend-1.0.0.dist-info/METADATA
dipend-1.0.0.dist-info/WHEEL
dipend-1.0.0.dist-info/top_level.txt
dipend-1.0.0.dist-info/RECORD
